Metadata-Version: 2.4
Name: pe-automator
Version: 0.20.3
Summary: PE Automator is a Python package for automating the setup and execution of parameter estimation (PE) runs using Bilby Pipe.
Home-page: https://git.ligo.org/yumeng.xu/pe-automator
Author: Yumeng Xu
Author-email: Yumeng Xu <yumeng.xu@ligo.org>
Keywords: ligo,gravitational waves,parameter estimation
Requires-Python: >=3.8
Requires-Dist: bilby-pipe
Requires-Dist: python-gitlab
Requires-Dist: jinja2
Requires-Dist: numpy
Requires-Dist: scipy
Requires-Dist: pandas
Requires-Dist: matplotlib
Requires-Dist: gwpy
Requires-Dist: h5py
Requires-Dist: streamlit
Requires-Dist: streamlit-aggrid
Requires-Dist: plotly
Requires-Dist: GitPython
Requires-Dist: click
Requires-Dist: paramiko
Requires-Dist: pymannkendall
Dynamic: author
Dynamic: description
Dynamic: description-content-type
Dynamic: home-page
Dynamic: requires-dist
Dynamic: requires-python
